deconvolution/__init__.py
deconvolution/deconvolve.py
deconvolution/params.py
deconvolution/simulate.py
deconvolution/utils.py
deconvolution/forward/__init__.py
deconvolution/forward/convolution.py
deconvolution/methods/ABC.py
deconvolution/methods/GARL.py
deconvolution/methods/RL.py
deconvolution/methods/RLTV.py
deconvolution/methods/Tikhonov.py
deconvolution/methods/__init__.py
deconvolution/methods/solver.py
deconvolution/methods/configs/__init__.py
deconvolution/methods/configs/GARL/__init__.py
deconvolution/methods/configs/GARL/airyscan_params.py
deconvolution/methods/configs/GARL/widefield_params.py
deconvolution/methods/models_GARL/__init__.py
deconvolution/methods/models_GARL/deep_equilibrium.py
deconvolution/methods/models_GARL/multi_conv.py
deconvolution/methods/models_GARL/spline_autograd_func.py
deconvolution/methods/models_GARL/spline_module.py
deconvolution/methods/models_GARL/spline_s_shape.py
deconvolution/methods/models_GARL/utils.py
deconvolution/methods/models_GARL/wc_conv_net.py
deconvolution/reader/__init__.py
deconvolution/reader/get_reader.py
deconvolution/reader/read_czi.py
deconvolution/reader/read_tif.py
forward/__init__.py
forward/convolution.py
methods/ABC.py
methods/GARL.py
methods/RL.py
methods/RLTV.py
methods/Tikhonov.py
methods/__init__.py
methods/solver.py
methods/configs/__init__.py
methods/configs/GARL/__init__.py
methods/configs/GARL/airyscan_params.py
methods/configs/GARL/widefield_params.py
methods/models_GARL/__init__.py
methods/models_GARL/deep_equilibrium.py
methods/models_GARL/multi_conv.py
methods/models_GARL/spline_autograd_func.py
methods/models_GARL/spline_module.py
methods/models_GARL/spline_s_shape.py
methods/models_GARL/utils.py
methods/models_GARL/wc_conv_net.py
pyxudeconv/__init__.py
pyxudeconv/deconvolve.py
pyxudeconv/deconvolution/__init__.py
pyxudeconv/deconvolution/deconvolve.py
pyxudeconv/deconvolution/params.py
pyxudeconv/deconvolution/simulate.py
pyxudeconv/deconvolution/utils.py
pyxudeconv-0.0.2.6.dist-info/LICENSE
pyxudeconv-0.0.2.6.dist-info/METADATA
pyxudeconv-0.0.2.6.dist-info/WHEEL
pyxudeconv-0.0.2.6.dist-info/top_level.txt
pyxudeconv-0.0.2.6.dist-info/RECORD
