Metadata-Version: 2.2
Name: pyxudeconv
Version: 0.0.2.6
Summary: 3D Deconvolution with Pyxu library
Author: Thanh-an Pham
Author-email: pham0204@gmail.com
License: 
Project-URL: Bug Tracker, https://github.com/ThanhAnPham/pyxudeconv/issues
Project-URL: Documentation, https://github.com/ThanhAnPham/pyxudeconv#README.md
Project-URL: Source Code, https://github.com/ThanhAnPham/pyxudeconv
Project-URL: User Support, https://github.com/ThanhAnPham/pyxudeconv/issues
Classifier: Development Status :: 2 - Pre-Alpha
Classifier: Intended Audience :: Developers
Classifier: License :: OSI Approved :: MIT License
Classifier: Operating System :: OS Independent
Classifier: Programming Language :: Python :: 3.10
Classifier: Programming Language :: Python :: 3.11
Classifier: Programming Language :: Python :: 3.12
Classifier: Topic :: Scientific/Engineering :: Image Processing
Requires-Python: <3.13,>=3.10
License-File: LICENSE
Requires-Dist: tifffile
Requires-Dist: pylibCZIrw
Requires-Dist: numpy
Requires-Dist: scipy
Requires-Dist: matplotlib
Requires-Dist: pyxu
Provides-Extra: gpu11
Requires-Dist: pyxu[complete11]; extra == "gpu11"
Provides-Extra: gpu12
Requires-Dist: pyxu[complete]; extra == "gpu12"
Provides-Extra: testing
Requires-Dist: tox; extra == "testing"
Requires-Dist: pytest; extra == "testing"
Requires-Dist: pytest-cov; extra == "testing"
